{
  "menus": [
    {
      "id": 1,
      "titre": "Yassa guinar",
      "description": "Yassa guinar bou nekh",
      "image": "Test",
      "prix": "2000"
    },
    {
      "id": 2,
      "titre": "Thieboudjene",
      "description": "Thieboudjene Penda Mbaye",
      "image": "Test",
      "prix": "1500"
    },
    {
      "id": 3,
      "titre": "Poulet frittes",
      "description": "Poulet frittes ",
      "image": "Test",
      "prix": "3000"
    },
    {
      "id": 4,
      "titre": "Soupou kandié",
      "description": "Soupou kandié bou nekh",
      "image": "Test",
      "prix": "2500"
    }
  ],
  "comments": [
    {
      "id": 1,
      "body": "some comment",
      "postId": 1
    }
  ],
  "profile": {
    "name": "typicode"
  }
}